hackbyte/__init__.py
hackbyte/__main__.py
hackbyte/cli.py
hackbyte/dummyproc.py
hackbyte/info.py
hackbyte/logs.py
hackbyte/memeditor.py
hackbyte/scanner.py
hackbyte/utils.py
hackbyte/valuetypes.py
hackbyte/version.py
hackbyte/ansi_colors/__init__.py
hackbyte/ansi_colors/ansi.py
hackbyte/ansi_colors/demo.py
hackbyte-2.0.dist-info/METADATA
hackbyte-2.0.dist-info/WHEEL
hackbyte-2.0.dist-info/entry_points.txt
hackbyte-2.0.dist-info/top_level.txt
hackbyte-2.0.dist-info/RECORD
