Metadata-Version: 2.4
Name: hackbyte
Version: 2.0
Summary: HackByte is a powerful CLI memory scanner and modifier for rooted Linux and Android.
Home-page: https://github.com/DX4GREY/hackbyte
Author: Dx4Grey
Author-email: dxablack@gmail.com
Keywords: memory scanner cli android root linux hacking freeze reverse-engineering
Classifier: Development Status :: 4 - Beta
Classifier: Intended Audience :: Developers
Classifier: Topic :: System :: Monitoring
Classifier: Operating System :: POSIX :: Linux
Classifier: Programming Language :: Python :: 3
Classifier: License :: OSI Approved :: MIT License
Requires-Python: >=3.6
Dynamic: author
Dynamic: author-email
Dynamic: classifier
Dynamic: description
Dynamic: description-content-type
Dynamic: home-page
Dynamic: keywords
Dynamic: requires-python
Dynamic: summary
